README.md
setup.py
crypto/__init__.py
crypto/simple.py
crypto/tests/__init__.py
crypto/tests/test.py
crypto_sum_alesanchezr.egg-info/PKG-INFO
crypto_sum_alesanchezr.egg-info/SOURCES.txt
crypto_sum_alesanchezr.egg-info/dependency_links.txt
crypto_sum_alesanchezr.egg-info/requires.txt
crypto_sum_alesanchezr.egg-info/top_level.txt